LICENSE
README.md
setup.py
galEupy/__init__.py
galEupy/__main__.py
galEupy/app.py
galEupy/commondata.py
galEupy/config_utility.py
galEupy/dbconnect.py
galEupy/dbschema.py
galEupy/dbtable_utility.py
galEupy/directory_utility.py
galEupy/general_utility.py
galEupy/genome.py
galEupy/process_tables.py
galEupy/processing_utility.py
galEupy/protein_annotation_utility.py
galEupy/taxomony.py
galEupy/version.py
galEupy.egg-info/PKG-INFO
galEupy.egg-info/SOURCES.txt
galEupy.egg-info/dependency_links.txt
galEupy.egg-info/entry_points.txt
galEupy.egg-info/requires.txt
galEupy.egg-info/top_level.txt
galEupy/BioFile/__init__.py
galEupy/BioFile/genbank_parser.py
galEupy/BioFile/gff_parser.py
galEupy/BioFile/gff_parser_pysam.py
galEupy/BioFile/interproscan_parser.py
galEupy/data/CommonData/GramStrain.txt
galEupy/data/CommonData/gene_code.out
galEupy/data/CommonData/goevidence.out
galEupy/data/CommonData/readme.txt
galEupy/data/CommonData/taxdump.tar.gz
galEupy/data/CommonData/taxon.out
galEupy/data/DbSchema/DoTS.sql
galEupy/data/DbSchema/SRes.sql
galEupy/data/DefaultConfig/database.ini
galEupy/data/DefaultConfig/organism_config_format.ini
galEupy/data/DefaultConfig/path.ini
galeupy/__init__.py
galeupy/__main__.py
galeupy/app.py
galeupy/commondata.py
galeupy/config_utility.py
galeupy/dbconnect.py
galeupy/dbschema.py
galeupy/dbtable_utility.py
galeupy/directory_utility.py
galeupy/general_utility.py
galeupy/genome.py
galeupy/process_tables.py
galeupy/processing_utility.py
galeupy/protein_annotation_utility.py
galeupy/taxomony.py
galeupy/version.py
galeupy.egg-info/PKG-INFO
galeupy.egg-info/SOURCES.txt
galeupy.egg-info/dependency_links.txt
galeupy.egg-info/entry_points.txt
galeupy.egg-info/requires.txt
galeupy.egg-info/top_level.txt
galeupy/BioFile/__init__.py
galeupy/BioFile/genbank_parser.py
galeupy/BioFile/gff_parser.py
galeupy/BioFile/gff_parser_pysam.py
galeupy/BioFile/interproscan_parser.py
galeupy/data/CommonData/GramStrain.txt
galeupy/data/CommonData/gene_code.out
galeupy/data/CommonData/goevidence.out
galeupy/data/CommonData/readme.txt
galeupy/data/CommonData/taxdump.tar.gz
galeupy/data/CommonData/taxon.out
galeupy/data/DbSchema/DoTS.sql
galeupy/data/DbSchema/SRes.sql
galeupy/data/DefaultConfig/database.ini
galeupy/data/DefaultConfig/organism_config_format.ini
galeupy/data/DefaultConfig/path.ini